kabyle_cleaner/__init__.py
kabyle_cleaner/_data.py
kabyle_cleaner/_fix.py
kabyle_cleaner/_io.py
kabyle_cleaner/_reflow.py
kabyle_cleaner/cli.py
kabyle_text_cleaner-0.1.0.dist-info/METADATA
kabyle_text_cleaner-0.1.0.dist-info/WHEEL
kabyle_text_cleaner-0.1.0.dist-info/entry_points.txt
kabyle_text_cleaner-0.1.0.dist-info/licenses/LICENSE
kabyle_text_cleaner-0.1.0.dist-info/RECORD
