Metadata-Version: 2.4
Name: kabyle-text-cleaner
Version: 0.1.0
Summary: Fix non-standard characters and optionally reflow Kabyle text
Project-URL: Homepage, https://github.com/Imsidag/kabyle-text-cleaner
Project-URL: Repository, https://github.com/Imsidag/kabyle-text-cleaner
Project-URL: Issues, https://github.com/Imsidag/kabyle-text-cleaner/issues
Author-email: Athmane MOKRAOUI <butterglyoffire+py@protonmail.com>
License: MIT
License-File: LICENSE
Classifier: Development Status :: 4 - Beta
Classifier: Environment :: Console
Classifier: Intended Audience :: Developers
Classifier: Intended Audience :: Science/Research
Classifier: License :: OSI Approved :: MIT License
Classifier: Operating System :: OS Independent
Classifier: Programming Language :: Python :: 3
Classifier: Programming Language :: Python :: 3.8
Classifier: Programming Language :: Python :: 3.9
Classifier: Programming Language :: Python :: 3.10
Classifier: Programming Language :: Python :: 3.11
Classifier: Programming Language :: Python :: 3.12
Classifier: Topic :: Text Processing :: Linguistic
Requires-Python: >=3.8
Provides-Extra: toml
Requires-Dist: tomli>=1.2.0; (python_version < '3.11') and extra == 'toml'
